torch_spline_conv/__init__.py
torch_spline_conv/_basis_cpu.so
torch_spline_conv/_basis_cuda.so
torch_spline_conv/_version_cpu.so
torch_spline_conv/_version_cuda.so
torch_spline_conv/_weighting_cpu.so
torch_spline_conv/_weighting_cuda.so
torch_spline_conv/basis.py
torch_spline_conv/conv.py
torch_spline_conv/testing.py
torch_spline_conv/weighting.py
torch_spline_conv_rocm-1.2.2.post2.dist-info/LICENSE
torch_spline_conv_rocm-1.2.2.post2.dist-info/METADATA
torch_spline_conv_rocm-1.2.2.post2.dist-info/RECORD
torch_spline_conv_rocm-1.2.2.post2.dist-info/WHEEL
torch_spline_conv_rocm-1.2.2.post2.dist-info/top_level.txt